dfrobot_environmental_sensor/__init__.py
dfrobot_environmental_sensor/constants.py
dfrobot_environmental_sensor/core.py
dfrobot_environmental_sensor/transports.py
dfrobot_environmental_sensor-2.1.2.dist-info/licenses/LICENSE
examples/read_all.py
tests/conftest.py
tests/test_core.py
tests/test_sensor.py
dfrobot_environmental_sensor-2.1.2.dist-info/METADATA
dfrobot_environmental_sensor-2.1.2.dist-info/WHEEL
dfrobot_environmental_sensor-2.1.2.dist-info/top_level.txt
dfrobot_environmental_sensor-2.1.2.dist-info/RECORD
