Metadata-Version: 2.4
Name: dfrobot-environmental-sensor
Version: 2.1.2
Summary: Python 3.8+ library for the DFRobot SEN0500/SEN0501 environmental sensor on Raspberry Pi.
Author-email: "DFRobot (original library)" <jie.tang@dfrobot.com>
Maintainer-email: Karl Lundgren <karl.lundgren@ri.se>
License: MIT License
Project-URL: Homepage, https://github.com/kallegrens/dfrobot-environmental-sensor
Project-URL: Source, https://github.com/kallegrens/dfrobot-environmental-sensor
Project-URL: Issues, https://github.com/kallegrens/dfrobot-environmental-sensor/issues
Project-URL: Changelog, https://github.com/kallegrens/dfrobot-environmental-sensor/blob/master/CHANGELOG.md
Keywords: DFRobot,SEN0500,SEN0501,environmental,sensor,I2C,UART,Raspberry Pi
Classifier: Development Status :: 5 - Production/Stable
Classifier: Intended Audience :: Developers
Classifier: License :: OSI Approved :: MIT License
Classifier: Operating System :: OS Independent
Classifier: Programming Language :: Python
Classifier: Programming Language :: Python :: 3
Classifier: Programming Language :: Python :: 3 :: Only
Classifier: Programming Language :: Python :: 3.8
Classifier: Programming Language :: Python :: 3.9
Classifier: Programming Language :: Python :: 3.10
Classifier: Programming Language :: Python :: 3.11
Classifier: Programming Language :: Python :: 3.12
Classifier: Topic :: Scientific/Engineering :: Atmospheric Science
Classifier: Topic :: Software Development :: Embedded Systems
Classifier: Topic :: System :: Hardware
Requires-Python: >=3.8
License-File: LICENSE
Requires-Dist: modbus-tk<2.0,>=1.0
Requires-Dist: smbus3<1.0,>=0.5
Dynamic: license-file
